pscript/__init__.py
pscript/base.py
pscript/commonast.py
pscript/functions.py
pscript/modules.py
pscript/parser0.py
pscript/parser1.py
pscript/parser2.py
pscript/parser3.py
pscript/stdlib.py
pscript/stubs.py
pscript/testing.py
pscript_legacy/__init__.py
pscript_legacy/base.py
pscript_legacy/commonast.py
pscript_legacy/functions.py
pscript_legacy/modules.py
pscript_legacy/parser0.py
pscript_legacy/parser1.py
pscript_legacy/parser2.py
pscript_legacy/parser3.py
pscript_legacy/stdlib.py
pscript_legacy/stubs.py
pscript_legacy/testing.py
pscript-0.7.7.dist-info/LICENSE
pscript-0.7.7.dist-info/METADATA
pscript-0.7.7.dist-info/WHEEL
pscript-0.7.7.dist-info/top_level.txt
pscript-0.7.7.dist-info/zip-safe
pscript-0.7.7.dist-info/RECORD
